pyloom/__init__.py
pyloom/class_resolver.py
pyloom/event_processor.py
pyloom/thread.py
pyloom/tree.py
pyloom-0.0.3.dist-info/LICENSE
pyloom-0.0.3.dist-info/METADATA
pyloom-0.0.3.dist-info/WHEEL
pyloom-0.0.3.dist-info/RECORD
