Metadata-Version: 2.1
Name: pyloom
Version: 0.0.3
Summary: A event sourcing framework for building large language model applications
Author: Teng "Niel" Hu
Author-email: hu.niel92@gmail.com
Requires-Python: >=3.9,<4.0
Classifier: Programming Language :: Python :: 3
Classifier: Programming Language :: Python :: 3.9
Classifier: Programming Language :: Python :: 3.10
Classifier: Programming Language :: Python :: 3.11
Requires-Dist: pyvis (==0.3.1)
